discorddataanalyzer/__init__.py
discorddataanalyzer-0.0.4.dist-info/LICENSE
discorddataanalyzer-0.0.4.dist-info/METADATA
discorddataanalyzer-0.0.4.dist-info/WHEEL
discorddataanalyzer-0.0.4.dist-info/top_level.txt
discorddataanalyzer-0.0.4.dist-info/RECORD
