Metadata-Version: 2.1
Name: discorddataanalyzer
Version: 0.0.4
Home-page: https://github.com/Aleph-Null-123/Discord-Data-Python-Module
Author: Arjun Naik
Author-email: arjunsatishnaik@gmail.com
Project-URL: Bug Tracker, https://github.com/Aleph-Null-123/Discord-Data-Python-Module/issues
Classifier: Programming Language :: Python :: 3
Classifier: License :: OSI Approved :: MIT License
Classifier: Operating System :: OS Independent
Requires-Python: >=3.6
License-File: LICENSE
Requires-Dist: pandas
Requires-Dist: matplotlib
Requires-Dist: numpy
Requires-Dist: pytz
Requires-Dist: tzlocal
Requires-Dist: emoji
